peft/__init__.py
peft/mapping.py
peft/peft_model.py
peft/tuners/__init__.py
peft/tuners/lora.py
peft/tuners/p_tuning.py
peft/tuners/prefix_tuning.py
peft/tuners/prompt_tuning.py
peft/utils/__init__.py
peft/utils/adapters_utils.py
peft/utils/config.py
peft/utils/other.py
peft/utils/save_and_load.py
peft_machinify-0.3.0.dev0.dist-info/LICENSE
peft_machinify-0.3.0.dev0.dist-info/METADATA
peft_machinify-0.3.0.dev0.dist-info/WHEEL
peft_machinify-0.3.0.dev0.dist-info/top_level.txt
peft_machinify-0.3.0.dev0.dist-info/RECORD
